docs/button.py
docs/conf.py
docs/cookieconsent.py
make_endpoint/__init__.py
make_endpoint/make_docs.py
python_amazon_sp_api_async-0.0.1.dist-info/licenses/LICENSE
sp_api_async/__init__.py
sp_api_async/__version__.py
sp_api_async/api/__init__.py
sp_api_async/api/amazon_warehousing_and_distribu/__init__.py
sp_api_async/api/amazon_warehousing_and_distribu/amazon_warehousing_and_distribu.py
sp_api_async/api/aplus_content/__init__.py
sp_api_async/api/aplus_content/aplus_content.py
sp_api_async/api/application_integrations/__init__.py
sp_api_async/api/application_integrations/application_integrations.py
sp_api_async/api/application_management/__init__.py
sp_api_async/api/application_management/application_management.py
sp_api_async/api/authorization/__init__.py
sp_api_async/api/authorization/authorization.py
sp_api_async/api/catalog/__init__.py
sp_api_async/api/catalog/catalog.py
sp_api_async/api/catalog_items/__init__.py
sp_api_async/api/catalog_items/catalog_items.py
sp_api_async/api/customer_feedback/__init__.py
sp_api_async/api/customer_feedback/customer_feedback.py
sp_api_async/api/data_kiosk/__init__.py
sp_api_async/api/data_kiosk/data_kiosk.py
sp_api_async/api/easy_ship/__init__.py
sp_api_async/api/easy_ship/easy_ship.py
sp_api_async/api/external_fulfillment/__init__.py
sp_api_async/api/external_fulfillment/external_fulfillment.py
sp_api_async/api/fba_inbound_eligibility/__init__.py
sp_api_async/api/fba_inbound_eligibility/fba_inbound_eligibility.py
sp_api_async/api/fba_small_and_light/__init__.py
sp_api_async/api/fba_small_and_light/fba_small_and_light.py
sp_api_async/api/feeds/__init__.py
sp_api_async/api/feeds/feeds.py
sp_api_async/api/finances/__init__.py
sp_api_async/api/finances/finances.py
sp_api_async/api/fulfillment_inbound/__init__.py
sp_api_async/api/fulfillment_inbound/fulfillment_inbound.py
sp_api_async/api/fulfillment_outbound/__init__.py
sp_api_async/api/fulfillment_outbound/fulfillment_outbound.py
sp_api_async/api/inventories/__init__.py
sp_api_async/api/inventories/inventories.py
python_amazon_sp_api_async-0.0.1.dist-info/METADATA
python_amazon_sp_api_async-0.0.1.dist-info/WHEEL
python_amazon_sp_api_async-0.0.1.dist-info/top_level.txt
python_amazon_sp_api_async-0.0.1.dist-info/RECORD
