Metadata-Version: 2.4
Name: python-amazon-sp-api-async
Version: 0.0.1
Summary: Python async wrapper for the Amazon Selling-Partner API
Author-email: Michael Primke <primke.michael@gmail.com>, zhang wenguang <zwgmlr3@gmail.com>
License-Expression: MIT
Project-URL: Homepage, https://github.com/zhangwg4apollo/python-amazon-sp-api-async
Project-URL: Documentation, https://github.com/zhangwg4apollo/python-amazon-sp-api-async
Project-URL: Repository, https://github.com/zhangwg4apollo/python-amazon-sp-api-async
Project-URL: Issues, https://github.com/zhangwg4apollo/python-amazon-sp-api-async/issues
Project-URL: Discussions, https://github.com/zhangwg4apollo/python-amazon-sp-api-async/discussions
Keywords: amazon,sp-api,selling-partner-api,amazon-api,marketplace,async,asyncio,httpx
Classifier: Development Status :: 4 - Beta
Classifier: Intended Audience :: Developers
Classifier: Operating System :: OS Independent
Classifier: Programming Language :: Python :: 3
Classifier: Programming Language :: Python :: 3.11
Classifier: Programming Language :: Python :: 3.12
Classifier: Programming Language :: Python :: 3.13
Classifier: Topic :: Software Development :: Libraries :: Python Modules
Classifier: Topic :: Internet :: WWW/HTTP
Requires-Python: >=3.13
License-File: LICENSE
Requires-Dist: cachetools>=4.2
Requires-Dist: confuse>=1.4
Requires-Dist: httpx>=0.27.0
Requires-Dist: jinja2>=3.1.6
Requires-Dist: pytz>=2021.1
Provides-Extra: aws
Requires-Dist: boto3>=1.17.0; extra == "aws"
Provides-Extra: aws-caching
Requires-Dist: aws-secretsmanager-caching; extra == "aws-caching"
Requires-Dist: boto3>=1.17.0; extra == "aws-caching"
Dynamic: license-file
